[
  {
    "title": "Junior Software Engineer",
    "company": "Jobs via Dice",
    "location": "Springfield, VA",
    "level": "Entry",
    "min_exp": 3.0,
    "job_url": "https://www.linkedin.com/jobs/view/4392138748",
    "date_posted": null,
    "keyword_score": 59,
    "site": "linkedin"
  },
  {
    "title": "Software Engineer [Multiple Positions Available]",
    "company": "JPMorganChase",
    "location": "Chicago, IL",
    "level": "Entry",
    "min_exp": null,
    "job_url": "https://www.linkedin.com/jobs/view/4393268093",
    "date_posted": null,
    "keyword_score": 56,
    "site": "linkedin"
  },
  {
    "title": "Software Engineer, (L2) Audiences & Journeys",
    "company": "Twilio",
    "location": "",
    "level": "Entry",
    "min_exp": 2.0,
    "job_url": "https://www.linkedin.com/jobs/view/4393241661",
    "date_posted": null,
    "keyword_score": 54,
    "site": "linkedin"
  },
  {
    "title": "Backend Developer - Internship (USA ONLY)",
    "company": "Park My Ride, LLC",
    "location": "",
    "level": "Entry",
    "min_exp": null,
    "job_url": "https://www.linkedin.com/jobs/view/4392156357",
    "date_posted": null,
    "keyword_score": 52,
    "site": "linkedin"
  },
  {
    "title": "Software Engineer I - Java - Bay Area (W2 Only)",
    "company": "Flexton Inc.",
    "location": "Sunnyvale, CA",
    "level": "Entry",
    "min_exp": null,
    "job_url": "https://www.linkedin.com/jobs/view/4391154624",
    "date_posted": null,
    "keyword_score": 49,
    "site": "linkedin"
  },
  {
    "title": "Software Engineer 2 (Full Stack - AI, SQL, React, Python)",
    "company": "U.S. Bank",
    "location": "Hopkins, MN",
    "level": "Entry",
    "min_exp": null,
    "job_url": "https://www.linkedin.com/jobs/view/4393247885",
    "date_posted": null,
    "keyword_score": 44,
    "site": "linkedin"
  },
  {
    "title": "Software Developer III",
    "company": "Spigen Inc",
    "location": "Irvine, CA",
    "level": "Entry",
    "min_exp": null,
    "job_url": "https://www.linkedin.com/jobs/view/4319166236",
    "date_posted": null,
    "keyword_score": 40,
    "site": "linkedin"
  },
  {
    "title": "Software Engineer, Vehicle Engineering",
    "company": "Tesla",
    "location": "Palo Alto, CA",
    "level": "Entry",
    "min_exp": null,
    "job_url": "https://www.linkedin.com/jobs/view/4393254398",
    "date_posted": null,
    "keyword_score": 39,
    "site": "linkedin"
  },
  {
    "title": "Software Developer",
    "company": "PNC",
    "location": "Pittsburgh, PA",
    "level": "Entry",
    "min_exp": null,
    "job_url": "https://www.linkedin.com/jobs/view/4393251920",
    "date_posted": null,
    "keyword_score": 38,
    "site": "linkedin"
  },
  {
    "title": "Software Engineer",
    "company": "Siemens",
    "location": "New York, NY",
    "level": "Entry",
    "min_exp": null,
    "job_url": "https://www.linkedin.com/jobs/view/4392167423",
    "date_posted": null,
    "keyword_score": 34,
    "site": "linkedin"
  },
  {
    "title": "Backend Software Engineer II \u2013 Go (Golang)",
    "company": "Medbridge",
    "location": "Bellevue, WA",
    "level": "Mid",
    "min_exp": null,
    "job_url": "https://www.linkedin.com/jobs/view/4392131715",
    "date_posted": null,
    "keyword_score": 32,
    "site": "linkedin"
  },
  {
    "title": "Software Engineer II - AWS",
    "company": "Travelers",
    "location": "Hartford, CT",
    "level": "Mid",
    "min_exp": null,
    "job_url": "https://www.linkedin.com/jobs/view/4392172052",
    "date_posted": null,
    "keyword_score": 32,
    "site": "linkedin"
  },
  {
    "title": "Software Developer 1",
    "company": "Inside Higher Ed",
    "location": "Stanford, CA",
    "level": "Entry",
    "min_exp": null,
    "job_url": "https://www.linkedin.com/jobs/view/4393240335",
    "date_posted": null,
    "keyword_score": 31,
    "site": "linkedin"
  },
  {
    "title": "Software Engineer 1",
    "company": "Lensa",
    "location": "New York, NY",
    "level": "Entry",
    "min_exp": null,
    "job_url": "https://www.linkedin.com/jobs/view/4393253469",
    "date_posted": null,
    "keyword_score": 31,
    "site": "linkedin"
  },
  {
    "title": "Software Engineer II",
    "company": "SICK Sensor Intelligence",
    "location": "Canton, MA",
    "level": "Mid",
    "min_exp": null,
    "job_url": "https://www.linkedin.com/jobs/view/4391304594",
    "date_posted": null,
    "keyword_score": 29,
    "site": "linkedin"
  },
  {
    "title": "Software Engineer (Full Stack)",
    "company": "BNY",
    "location": "Lake Mary, FL",
    "level": "Entry",
    "min_exp": null,
    "job_url": "https://www.linkedin.com/jobs/view/4344905589",
    "date_posted": null,
    "keyword_score": 27,
    "site": "linkedin"
  },
  {
    "title": "Software Engineer III, Community Builders",
    "company": "Reddit, Inc.",
    "location": "",
    "level": "Mid",
    "min_exp": null,
    "job_url": "https://www.linkedin.com/jobs/view/4392144737",
    "date_posted": null,
    "keyword_score": 23,
    "site": "linkedin"
  },
  {
    "title": "junior data scientist/java backend developer",
    "company": "SynergisticIT",
    "location": "Long Beach, CA",
    "level": "New Grad",
    "min_exp": null,
    "job_url": "https://www.linkedin.com/jobs/view/4392133811",
    "date_posted": null,
    "keyword_score": 21,
    "site": "linkedin"
  },
  {
    "title": "Software Engineer, Bridge",
    "company": "Stripe",
    "location": "",
    "level": "Entry",
    "min_exp": null,
    "job_url": "https://www.linkedin.com/jobs/view/4366978046",
    "date_posted": null,
    "keyword_score": 20,
    "site": "linkedin"
  },
  {
    "title": "Software Engineer I",
    "company": "Hewlett Packard Enterprise",
    "location": "Roseville, CA",
    "level": "Entry",
    "min_exp": 2.0,
    "job_url": "https://www.linkedin.com/jobs/view/4393265812",
    "date_posted": null,
    "keyword_score": 20,
    "site": "linkedin"
  },
  {
    "title": "Software Engineer II",
    "company": "Jobs via Dice",
    "location": "Redmond, WA",
    "level": "Mid",
    "min_exp": null,
    "job_url": "https://www.linkedin.com/jobs/view/4392136782",
    "date_posted": null,
    "keyword_score": 18,
    "site": "linkedin"
  },
  {
    "title": "Physics/Math Graduate - Entry Level Software Developer",
    "company": "Lensa",
    "location": "Vienna, VA",
    "level": "Entry",
    "min_exp": null,
    "job_url": "https://www.linkedin.com/jobs/view/4393252637",
    "date_posted": null,
    "keyword_score": 17,
    "site": "linkedin"
  },
  {
    "title": "Jr. Software Developer",
    "company": "Lensa",
    "location": "",
    "level": "Entry",
    "min_exp": null,
    "job_url": "https://www.linkedin.com/jobs/view/4393258105",
    "date_posted": null,
    "keyword_score": 17,
    "site": "linkedin"
  },
  {
    "title": "Sightline Software Engineer (Sightline Information Technology)",
    "company": "Inside Higher Ed",
    "location": "Baltimore, MD",
    "level": "Entry",
    "min_exp": null,
    "job_url": "https://www.linkedin.com/jobs/view/4393230805",
    "date_posted": null,
    "keyword_score": 17,
    "site": "linkedin"
  },
  {
    "title": "Jr Software Developer",
    "company": "Bunzl Distribution NA",
    "location": "Missouri, United States",
    "level": "Entry",
    "min_exp": null,
    "job_url": "https://www.linkedin.com/jobs/view/4392161373",
    "date_posted": null,
    "keyword_score": 16,
    "site": "linkedin"
  },
  {
    "title": "Software Engineer II, Backend (Marketplace Performance)",
    "company": "Affirm",
    "location": "Seattle, WA",
    "level": "Mid",
    "min_exp": null,
    "job_url": "https://www.linkedin.com/jobs/view/4392130625",
    "date_posted": null,
    "keyword_score": 16,
    "site": "linkedin"
  },
  {
    "title": "Software Engineer III (Typescript, Java, Python, AI) (US)",
    "company": "TD Securities",
    "location": "Mount Laurel, NJ",
    "level": "Mid",
    "min_exp": 7.0,
    "job_url": "https://www.linkedin.com/jobs/view/4392996886",
    "date_posted": null,
    "keyword_score": 15,
    "site": "linkedin"
  }
]