[
  {
    "title": "Software Engineer (Java)",
    "company": "Wiraa",
    "location": "",
    "level": "Entry",
    "job_url": "https://www.linkedin.com/jobs/view/4390349000",
    "date_posted": null,
    "score": 20,
    "competition_score": 1
  },
  {
    "title": "Contract role: Java Software Engineer at  Oakland, CA or Alpharetta, GA (Onsite - Hybrid Model) - Locals Preferred - F2F",
    "company": "Yochana",
    "location": "Alpharetta, GA",
    "level": "Entry",
    "job_url": "https://www.linkedin.com/jobs/view/4390294246",
    "date_posted": null,
    "score": 20,
    "competition_score": 1
  },
  {
    "title": "Software Development Engineer III - Backend",
    "company": "Purpose Brands, LLC",
    "location": "Woodbury, MN",
    "level": "Entry",
    "job_url": "https://www.linkedin.com/jobs/view/4390279717",
    "date_posted": null,
    "score": 19,
    "competition_score": 1
  },
  {
    "title": "Software Engineer- Data",
    "company": "Wiraa",
    "location": "",
    "level": "Entry",
    "job_url": "https://www.linkedin.com/jobs/view/4390347095",
    "date_posted": null,
    "score": 14,
    "competition_score": 1
  },
  {
    "title": "Software Engineer - Founder's Office",
    "company": "CommerceIQ",
    "location": "Mountain View, CA",
    "level": "Entry",
    "job_url": "https://www.linkedin.com/jobs/view/4390284472",
    "date_posted": null,
    "score": 13,
    "competition_score": 1
  },
  {
    "title": "Software Engineer",
    "company": "Jobright.ai",
    "location": "",
    "level": "Entry",
    "job_url": "https://www.linkedin.com/jobs/view/4390298086",
    "date_posted": null,
    "score": 10,
    "competition_score": 1
  },
  {
    "title": "Java Software Developer",
    "company": "BeaconFire Inc.",
    "location": "New Jersey, United States",
    "level": "Entry",
    "job_url": "https://www.linkedin.com/jobs/view/4386687508",
    "date_posted": null,
    "score": 9,
    "competition_score": 1
  },
  {
    "title": "Backend Software Engineer",
    "company": "Wiraa",
    "location": "",
    "level": "Entry",
    "job_url": "https://www.linkedin.com/jobs/view/4390339558",
    "date_posted": null,
    "score": 9,
    "competition_score": 1
  },
  {
    "title": "Software Engineer (Full Stack)",
    "company": "Sandberg Goldberg Bernthal Family Foundation",
    "location": "",
    "level": "Entry",
    "job_url": "https://www.linkedin.com/jobs/view/4390279713",
    "date_posted": null,
    "score": 8,
    "competition_score": 1
  },
  {
    "title": "Software Developer",
    "company": "GoAuto Insurance",
    "location": "Chattanooga, TN",
    "level": "Entry",
    "job_url": "https://www.linkedin.com/jobs/view/4390289378",
    "date_posted": null,
    "score": 4,
    "competition_score": 1
  },
  {
    "title": "Software Engineer (C#, SQL)",
    "company": "Wiraa",
    "location": "",
    "level": "Entry",
    "job_url": "https://www.linkedin.com/jobs/view/4390339560",
    "date_posted": null,
    "score": 4,
    "competition_score": 1
  },
  {
    "title": "Software Engineer, AI",
    "company": "Wiraa",
    "location": "",
    "level": "Entry",
    "job_url": "https://www.linkedin.com/jobs/view/4390337629",
    "date_posted": null,
    "score": 3,
    "competition_score": 1
  },
  {
    "title": "Quantum/QEC Software Engineer:  $150-175K + Equity",
    "company": "IC Resources",
    "location": "Boston, MA",
    "level": "Entry",
    "job_url": "https://www.linkedin.com/jobs/view/4384392416",
    "date_posted": null,
    "score": 3,
    "competition_score": 1
  },
  {
    "title": "Software Developer",
    "company": "eTeam",
    "location": "San Jose, CA",
    "level": "Entry",
    "job_url": "https://www.linkedin.com/jobs/view/4390289405",
    "date_posted": null,
    "score": 0,
    "competition_score": 1
  },
  {
    "title": "Embedded Software Engineer",
    "company": "Intellectt Inc",
    "location": "Redmond, WA",
    "level": "Entry",
    "job_url": "https://www.linkedin.com/jobs/view/4390286496",
    "date_posted": null,
    "score": 0,
    "competition_score": 0
  },
  {
    "title": "Software Engineer, Vehicle Control",
    "company": "Danfoss",
    "location": "Minneapolis, MN",
    "level": "Entry",
    "job_url": "https://www.linkedin.com/jobs/view/4390608376",
    "date_posted": null,
    "score": 0,
    "competition_score": 1
  },
  {
    "title": "Embedded Software Engineer",
    "company": "Fortinet",
    "location": "Sunnyvale, CA",
    "level": "Entry",
    "job_url": "https://www.linkedin.com/jobs/view/4390623758",
    "date_posted": null,
    "score": 0,
    "competition_score": 0
  },
  {
    "title": "Software Engineer",
    "company": "Aditi Consulting",
    "location": "Bellevue, WA",
    "level": "Entry",
    "job_url": "https://www.linkedin.com/jobs/view/4390636533",
    "date_posted": null,
    "score": 0,
    "competition_score": 1
  }
]