[
  {
    "title": "Software Engineer III, Full Stack, Search",
    "company": "Google",
    "location": "Mountain View, CA",
    "level": "Mid",
    "min_exp": 2.0,
    "max_exp": 2.0,
    "job_url": "https://www.linkedin.com/jobs/view/4394201462",
    "date_posted": null,
    "priority_score": 40,
    "score_pct": 31,
    "site": "linkedin"
  },
  {
    "title": "Software Engineer III, AI/ML, Google Cloud AI",
    "company": "Google",
    "location": "Sunnyvale, CA",
    "level": "Mid",
    "min_exp": 1.0,
    "max_exp": 2.0,
    "job_url": "https://www.linkedin.com/jobs/view/4365573964",
    "date_posted": null,
    "priority_score": 39,
    "score_pct": 30,
    "site": "linkedin"
  },
  {
    "title": "Software Engineer (L5) - Experimentation Platform",
    "company": "Netflix",
    "location": "",
    "level": "Entry",
    "min_exp": null,
    "max_exp": null,
    "job_url": "https://www.linkedin.com/jobs/view/4397581182",
    "date_posted": null,
    "priority_score": 37,
    "score_pct": 28,
    "site": "linkedin"
  },
  {
    "title": "Software Engineer III, Mobile, Android",
    "company": "Google",
    "location": "San Jose, CA",
    "level": "Mid",
    "min_exp": 2.0,
    "max_exp": 2.0,
    "job_url": "https://www.linkedin.com/jobs/view/4393873688",
    "date_posted": null,
    "priority_score": 33,
    "score_pct": 25,
    "site": "linkedin"
  },
  {
    "title": "Software Engineer, Edge TPU Compilers, Silicon",
    "company": "Google",
    "location": "Mountain View, CA",
    "level": "Entry",
    "min_exp": 1.0,
    "max_exp": 2.0,
    "job_url": "https://www.linkedin.com/jobs/view/4393863664",
    "date_posted": null,
    "priority_score": -999,
    "score_pct": 0,
    "site": "linkedin"
  },
  {
    "title": "Software Engineer, iOS, Level 4",
    "company": "Snap Inc.",
    "location": "Palo Alto, CA",
    "level": "Entry",
    "min_exp": null,
    "max_exp": null,
    "job_url": "https://www.linkedin.com/jobs/view/4354659420",
    "date_posted": null,
    "priority_score": -999,
    "score_pct": 0,
    "site": "linkedin"
  },
  {
    "title": "Software Engineer, Computer Vision, Geo",
    "company": "Google",
    "location": "Mountain View, CA",
    "level": "Entry",
    "min_exp": 1.0,
    "max_exp": 2.0,
    "job_url": "https://www.linkedin.com/jobs/view/4393872653",
    "date_posted": null,
    "priority_score": -999,
    "score_pct": 0,
    "site": "linkedin"
  },
  {
    "title": "Software Engineer, Machine Learning Infrastructure",
    "company": "Stripe",
    "location": "New York, United States",
    "level": "Entry",
    "min_exp": null,
    "max_exp": null,
    "job_url": "https://www.linkedin.com/jobs/view/4397366151",
    "date_posted": null,
    "priority_score": -999,
    "score_pct": 0,
    "site": "linkedin"
  }
]