[
  {
    "title": "Java Software Engineer",
    "company": "Mastech Digital",
    "location": "Pittsburgh, PA",
    "level": "Entry",
    "min_exp": null,
    "max_exp": null,
    "job_url": "https://www.linkedin.com/jobs/view/4397047431",
    "date_posted": null,
    "batch_time": "2026-04-02T18:15:47Z",
    "score": 123,
    "score_pct": 95,
    "competition_score": 0,
    "site": "linkedin"
  },
  {
    "title": "Software Engineer II",
    "company": "Mastercard",
    "location": "O'Fallon, MO",
    "level": "Mid",
    "min_exp": null,
    "max_exp": null,
    "job_url": "https://www.linkedin.com/jobs/view/4372402633",
    "date_posted": null,
    "batch_time": "2026-04-02T18:15:47Z",
    "score": 108,
    "score_pct": 83,
    "competition_score": 0,
    "site": "linkedin"
  },
  {
    "title": "API Backend Developer",
    "company": "Elsevier",
    "location": "Philadelphia, PA",
    "level": "Mid",
    "min_exp": null,
    "max_exp": null,
    "job_url": "https://www.linkedin.com/jobs/view/4393488053",
    "date_posted": null,
    "batch_time": "2026-04-02T18:15:47Z",
    "score": 102,
    "score_pct": 78,
    "competition_score": 0,
    "site": "linkedin"
  },
  {
    "title": "Full Stack Software Engineer - Growth",
    "company": "Perplexity",
    "location": "San Francisco, CA",
    "level": "Entry",
    "min_exp": null,
    "max_exp": null,
    "job_url": "https://www.linkedin.com/jobs/view/4370733991",
    "date_posted": null,
    "batch_time": "2026-04-02T18:15:47Z",
    "score": 79,
    "score_pct": 61,
    "competition_score": 0,
    "site": "linkedin"
  },
  {
    "title": "Full Stack Software Engineer",
    "company": "Perplexity",
    "location": "San Francisco, CA",
    "level": "Entry",
    "min_exp": null,
    "max_exp": null,
    "job_url": "https://www.linkedin.com/jobs/view/4322093864",
    "date_posted": null,
    "batch_time": "2026-04-02T18:15:47Z",
    "score": 79,
    "score_pct": 61,
    "competition_score": 0,
    "site": "linkedin"
  },
  {
    "title": "Full Stack Software Engineer - Applied AI",
    "company": "Perplexity",
    "location": "Palo Alto, CA",
    "level": "Entry",
    "min_exp": null,
    "max_exp": null,
    "job_url": "https://www.linkedin.com/jobs/view/4370732958",
    "date_posted": null,
    "batch_time": "2026-04-02T18:15:47Z",
    "score": 79,
    "score_pct": 61,
    "competition_score": 0,
    "site": "linkedin"
  },
  {
    "title": "Full Stack Software Engineer - Finance",
    "company": "Perplexity",
    "location": "San Francisco, CA",
    "level": "Entry",
    "min_exp": null,
    "max_exp": null,
    "job_url": "https://www.linkedin.com/jobs/view/4370792720",
    "date_posted": null,
    "batch_time": "2026-04-02T18:15:47Z",
    "score": 79,
    "score_pct": 61,
    "competition_score": 0,
    "site": "linkedin"
  },
  {
    "title": "Software Engineer II, Devices",
    "company": "EnergyHub",
    "location": "Brooklyn, NY",
    "level": "Mid",
    "min_exp": null,
    "max_exp": null,
    "job_url": "https://www.linkedin.com/jobs/view/4395347884",
    "date_posted": null,
    "batch_time": "2026-04-02T18:15:47Z",
    "score": 78,
    "score_pct": 60,
    "competition_score": 0,
    "site": "linkedin"
  },
  {
    "title": "Bioinformatics Software Engineer",
    "company": "Memorial Sloan Kettering Cancer Center",
    "location": "New York, NY",
    "level": "Entry",
    "min_exp": null,
    "max_exp": null,
    "job_url": "https://www.linkedin.com/jobs/view/4378539554",
    "date_posted": null,
    "batch_time": "2026-04-02T18:15:47Z",
    "score": 73,
    "score_pct": 56,
    "competition_score": 0,
    "site": "linkedin"
  },
  {
    "title": "Fullstack/ Backend Engineer",
    "company": "Qualitest",
    "location": "Menlo Park, CA",
    "level": "Entry",
    "min_exp": null,
    "max_exp": null,
    "job_url": "https://www.linkedin.com/jobs/view/4393468596",
    "date_posted": null,
    "batch_time": "2026-04-02T18:15:47Z",
    "score": 70,
    "score_pct": 54,
    "competition_score": 0,
    "site": "linkedin"
  },
  {
    "title": "Software Engineer",
    "company": "Jobright.ai",
    "location": "",
    "level": "Entry",
    "min_exp": 1.0,
    "max_exp": 2.0,
    "job_url": "https://www.linkedin.com/jobs/view/4395327555",
    "date_posted": null,
    "batch_time": "2026-04-02T18:15:47Z",
    "score": 61,
    "score_pct": 47,
    "competition_score": 0,
    "site": "linkedin"
  },
  {
    "title": "Java Software Engineer",
    "company": "SIMARN Solutions",
    "location": "New Jersey, United States",
    "level": "Entry",
    "min_exp": null,
    "max_exp": null,
    "job_url": "https://www.linkedin.com/jobs/view/4395360163",
    "date_posted": null,
    "batch_time": "2026-04-02T18:15:47Z",
    "score": 59,
    "score_pct": 45,
    "competition_score": 0,
    "site": "linkedin"
  },
  {
    "title": "Software Engineer in Test -- SINDC5499815",
    "company": "Compunnel Inc.",
    "location": "",
    "level": "Entry",
    "min_exp": null,
    "max_exp": null,
    "job_url": "https://www.linkedin.com/jobs/view/4395353618",
    "date_posted": null,
    "batch_time": "2026-04-02T18:15:47Z",
    "score": 50,
    "score_pct": 38,
    "competition_score": 0,
    "site": "linkedin"
  },
  {
    "title": "Software Developer [208452]",
    "company": "Aquent",
    "location": "Fremont, CA",
    "level": "Entry",
    "min_exp": null,
    "max_exp": null,
    "job_url": "https://www.linkedin.com/jobs/view/4384564336",
    "date_posted": null,
    "batch_time": "2026-04-02T18:15:47Z",
    "score": 50,
    "score_pct": 38,
    "competition_score": 0,
    "site": "linkedin"
  },
  {
    "title": "Full-stack Engineer (backend-leaning)",
    "company": "Pinwheel",
    "location": "New York, NY",
    "level": "Entry",
    "min_exp": null,
    "max_exp": null,
    "job_url": "https://www.linkedin.com/jobs/view/4395352372",
    "date_posted": null,
    "batch_time": "2026-04-02T18:15:47Z",
    "score": 49,
    "score_pct": 38,
    "competition_score": 0,
    "site": "linkedin"
  },
  {
    "title": "Software Engineer, Global Banking & Markets, Investment Banking",
    "company": "Goldman Sachs",
    "location": "Dallas, TX",
    "level": "Entry",
    "min_exp": null,
    "max_exp": null,
    "job_url": "https://www.linkedin.com/jobs/view/4373082505",
    "date_posted": null,
    "batch_time": "2026-04-02T18:15:47Z",
    "score": 47,
    "score_pct": 36,
    "competition_score": 0,
    "site": "linkedin"
  },
  {
    "title": "Software Developer (MuleSoft)",
    "company": "COUNTRY Financial\u00ae",
    "location": "Bloomington, IL",
    "level": "Entry",
    "min_exp": null,
    "max_exp": null,
    "job_url": "https://www.linkedin.com/jobs/view/4338154627",
    "date_posted": null,
    "batch_time": "2026-04-02T18:15:47Z",
    "score": 46,
    "score_pct": 35,
    "competition_score": 0,
    "site": "linkedin"
  },
  {
    "title": "Application Software Developer",
    "company": "Auxilior Capital Partners, Inc.",
    "location": "Philadelphia, PA",
    "level": "Entry",
    "min_exp": null,
    "max_exp": null,
    "job_url": "https://www.linkedin.com/jobs/view/4395228800",
    "date_posted": null,
    "batch_time": "2026-04-02T18:15:47Z",
    "score": 45,
    "score_pct": 35,
    "competition_score": 0,
    "site": "linkedin"
  },
  {
    "title": "Software Engineer II",
    "company": "Ironclad",
    "location": "San Francisco, CA",
    "level": "Mid",
    "min_exp": null,
    "max_exp": null,
    "job_url": "https://www.linkedin.com/jobs/view/4361577070",
    "date_posted": null,
    "batch_time": "2026-04-02T18:15:47Z",
    "score": 44,
    "score_pct": 34,
    "competition_score": 0,
    "site": "linkedin"
  },
  {
    "title": "Software Engineer, Data Privacy",
    "company": "Temu",
    "location": "",
    "level": "Entry",
    "min_exp": null,
    "max_exp": null,
    "job_url": "https://www.linkedin.com/jobs/view/4393489226",
    "date_posted": null,
    "batch_time": "2026-04-02T18:15:47Z",
    "score": 42,
    "score_pct": 32,
    "competition_score": 0,
    "site": "linkedin"
  },
  {
    "title": "Full-Stack Software Engineer II (JavaScript)",
    "company": "Kensho Technologies",
    "location": "Cambridge, MA",
    "level": "Mid",
    "min_exp": null,
    "max_exp": null,
    "job_url": "https://www.linkedin.com/jobs/view/4366944509",
    "date_posted": null,
    "batch_time": "2026-04-02T18:15:47Z",
    "score": 40,
    "score_pct": 31,
    "competition_score": 0,
    "site": "linkedin"
  },
  {
    "title": "Software Engineer III, Full Stack, Google Ads",
    "company": "Google",
    "location": "Irvine, CA",
    "level": "Mid",
    "min_exp": 2.0,
    "max_exp": 2.0,
    "job_url": "https://www.linkedin.com/jobs/view/4362564938",
    "date_posted": null,
    "batch_time": "2026-04-02T18:15:47Z",
    "score": 39,
    "score_pct": 30,
    "competition_score": 5,
    "site": "linkedin"
  },
  {
    "title": "Backend Software Engineer",
    "company": "Sundayy",
    "location": "",
    "level": "Entry",
    "min_exp": null,
    "max_exp": null,
    "job_url": "https://www.linkedin.com/jobs/view/4395297044",
    "date_posted": null,
    "batch_time": "2026-04-02T18:15:47Z",
    "score": 38,
    "score_pct": 29,
    "competition_score": 0,
    "site": "linkedin"
  },
  {
    "title": "ENTRY LEVEL SOFTWARE DEVELOPER",
    "company": "DeltaCode",
    "location": "",
    "level": "Entry",
    "min_exp": null,
    "max_exp": null,
    "job_url": "https://www.linkedin.com/jobs/view/4397083088",
    "date_posted": null,
    "batch_time": "2026-04-02T18:15:47Z",
    "score": 38,
    "score_pct": 29,
    "competition_score": 0,
    "site": "linkedin"
  },
  {
    "title": "Software Engineer III, Front End, Agent Assist",
    "company": "Google",
    "location": "Boulder, CO",
    "level": "Mid",
    "min_exp": 1.0,
    "max_exp": 2.0,
    "job_url": "https://www.linkedin.com/jobs/view/4393482351",
    "date_posted": null,
    "batch_time": "2026-04-02T18:15:47Z",
    "score": 37,
    "score_pct": 28,
    "competition_score": 5,
    "site": "linkedin"
  },
  {
    "title": "Software Engineer, GenAI",
    "company": "Abridge",
    "location": "New York, NY",
    "level": "Entry",
    "min_exp": null,
    "max_exp": null,
    "job_url": "https://www.linkedin.com/jobs/view/4384352482",
    "date_posted": null,
    "batch_time": "2026-04-02T18:15:47Z",
    "score": 35,
    "score_pct": 27,
    "competition_score": 0,
    "site": "linkedin"
  },
  {
    "title": "Mid level Software Engineer (Python or Java) - Up to $150,000",
    "company": "Hunter Bond",
    "location": "Boston, MA",
    "level": "Mid",
    "min_exp": null,
    "max_exp": null,
    "job_url": "https://www.linkedin.com/jobs/view/4397081016",
    "date_posted": null,
    "batch_time": "2026-04-02T18:15:47Z",
    "score": 34,
    "score_pct": 26,
    "competition_score": 0,
    "site": "linkedin"
  },
  {
    "title": "Remote Software Developer",
    "company": "Turing",
    "location": "California, United States",
    "level": "Entry",
    "min_exp": null,
    "max_exp": null,
    "job_url": "https://www.linkedin.com/jobs/view/4395368297",
    "date_posted": null,
    "batch_time": "2026-04-02T18:15:47Z",
    "score": 34,
    "score_pct": 26,
    "competition_score": 0,
    "site": "linkedin"
  },
  {
    "title": "Remote Software Engineer (US)",
    "company": "Turing",
    "location": "Atlanta, GA",
    "level": "Entry",
    "min_exp": null,
    "max_exp": null,
    "job_url": "https://www.linkedin.com/jobs/view/4395359134",
    "date_posted": null,
    "batch_time": "2026-04-02T18:15:47Z",
    "score": 34,
    "score_pct": 26,
    "competition_score": 0,
    "site": "linkedin"
  },
  {
    "title": "Infrastructure Systems Software Engineer",
    "company": "NVIDIA",
    "location": "Santa Clara, CA",
    "level": "Entry",
    "min_exp": null,
    "max_exp": null,
    "job_url": "https://www.linkedin.com/jobs/view/4384541713",
    "date_posted": null,
    "batch_time": "2026-04-02T18:15:47Z",
    "score": 31,
    "score_pct": 24,
    "competition_score": 0,
    "site": "linkedin"
  },
  {
    "title": "Software Engineer",
    "company": "Haystack",
    "location": "New York, NY",
    "level": "Entry",
    "min_exp": null,
    "max_exp": null,
    "job_url": "https://www.linkedin.com/jobs/view/4393482333",
    "date_posted": null,
    "batch_time": "2026-04-02T18:15:47Z",
    "score": 30,
    "score_pct": 23,
    "competition_score": 0,
    "site": "linkedin"
  },
  {
    "title": "Robotics Software Engineer",
    "company": "Formic",
    "location": "Woodridge, IL",
    "level": "Entry",
    "min_exp": null,
    "max_exp": null,
    "job_url": "https://www.linkedin.com/jobs/view/4366527534",
    "date_posted": null,
    "batch_time": "2026-04-02T18:15:47Z",
    "score": 29,
    "score_pct": 22,
    "competition_score": 0,
    "site": "linkedin"
  },
  {
    "title": "Software Engineer (Js, Figma)",
    "company": "Sundayy",
    "location": "",
    "level": "Entry",
    "min_exp": null,
    "max_exp": null,
    "job_url": "https://www.linkedin.com/jobs/view/4395288510",
    "date_posted": null,
    "batch_time": "2026-04-02T18:15:47Z",
    "score": 29,
    "score_pct": 22,
    "competition_score": 0,
    "site": "linkedin"
  },
  {
    "title": "[2026] Software Engineer, Creator - Early Career",
    "company": "Roblox",
    "location": "San Mateo, CA",
    "level": "Entry",
    "min_exp": null,
    "max_exp": null,
    "job_url": "https://www.linkedin.com/jobs/view/4366412419",
    "date_posted": null,
    "batch_time": "2026-04-02T18:15:47Z",
    "score": 29,
    "score_pct": 22,
    "competition_score": 0,
    "site": "linkedin"
  },
  {
    "title": "Software Engineer (Applications)",
    "company": "DataAnnotation",
    "location": "North Carolina, United States",
    "level": "Entry",
    "min_exp": null,
    "max_exp": null,
    "job_url": "https://www.linkedin.com/jobs/view/4304450490",
    "date_posted": null,
    "batch_time": "2026-04-02T18:15:47Z",
    "score": 28,
    "score_pct": 22,
    "competition_score": 0,
    "site": "linkedin"
  },
  {
    "title": "Backend Software Engineer",
    "company": "DataAnnotation",
    "location": "New Hampshire, United States",
    "level": "Entry",
    "min_exp": null,
    "max_exp": null,
    "job_url": "https://www.linkedin.com/jobs/view/4374792837",
    "date_posted": null,
    "batch_time": "2026-04-02T18:15:47Z",
    "score": 28,
    "score_pct": 22,
    "competition_score": 0,
    "site": "linkedin"
  },
  {
    "title": "Software Engineer, Frontend",
    "company": "Ivo",
    "location": "",
    "level": "Entry",
    "min_exp": null,
    "max_exp": null,
    "job_url": "https://www.linkedin.com/jobs/view/4339360663",
    "date_posted": null,
    "batch_time": "2026-04-02T18:15:47Z",
    "score": 28,
    "score_pct": 22,
    "competition_score": 0,
    "site": "linkedin"
  },
  {
    "title": "Database Software Developer",
    "company": "DataAnnotation",
    "location": "Kentucky, United States",
    "level": "Entry",
    "min_exp": null,
    "max_exp": null,
    "job_url": "https://www.linkedin.com/jobs/view/4304433755",
    "date_posted": null,
    "batch_time": "2026-04-02T18:15:47Z",
    "score": 28,
    "score_pct": 22,
    "competition_score": 0,
    "site": "linkedin"
  },
  {
    "title": "Software Developer",
    "company": "DataAnnotation",
    "location": "California, United States",
    "level": "Entry",
    "min_exp": null,
    "max_exp": null,
    "job_url": "https://www.linkedin.com/jobs/view/4304437844",
    "date_posted": null,
    "batch_time": "2026-04-02T18:15:47Z",
    "score": 28,
    "score_pct": 22,
    "competition_score": 0,
    "site": "linkedin"
  },
  {
    "title": "Software Engineer (Java/Python) - Up to $200k",
    "company": "Hunter Bond",
    "location": "Boston, MA",
    "level": "Entry",
    "min_exp": null,
    "max_exp": null,
    "job_url": "https://www.linkedin.com/jobs/view/4397071225",
    "date_posted": null,
    "batch_time": "2026-04-02T18:15:47Z",
    "score": 28,
    "score_pct": 22,
    "competition_score": 0,
    "site": "linkedin"
  },
  {
    "title": "Software Engineer, Energy Sales Platform ($175k - $235k + equity) at Gridmatic",
    "company": "Standout",
    "location": "Cupertino, CA",
    "level": "Entry",
    "min_exp": null,
    "max_exp": null,
    "job_url": "https://www.linkedin.com/jobs/view/4396678094",
    "date_posted": null,
    "batch_time": "2026-04-02T18:15:47Z",
    "score": 27,
    "score_pct": 21,
    "competition_score": 0,
    "site": "linkedin"
  },
  {
    "title": "Software Developer III",
    "company": "Dayforce",
    "location": "",
    "level": "Entry",
    "min_exp": null,
    "max_exp": null,
    "job_url": "https://www.linkedin.com/jobs/view/4382795909",
    "date_posted": null,
    "batch_time": "2026-04-02T18:15:47Z",
    "score": 27,
    "score_pct": 21,
    "competition_score": 0,
    "site": "linkedin"
  },
  {
    "title": "Software Developer",
    "company": "Kratos Defense and Security Solutions",
    "location": "Lanham, MD",
    "level": "Entry",
    "min_exp": null,
    "max_exp": null,
    "job_url": "https://www.linkedin.com/jobs/view/4334139857",
    "date_posted": null,
    "batch_time": "2026-04-02T18:15:47Z",
    "score": 27,
    "score_pct": 21,
    "competition_score": 0,
    "site": "linkedin"
  },
  {
    "title": "Software Engineer - Fellow",
    "company": "Siemens",
    "location": "Fremont, CA",
    "level": "Entry",
    "min_exp": null,
    "max_exp": null,
    "job_url": "https://www.linkedin.com/jobs/view/4383254835",
    "date_posted": null,
    "batch_time": "2026-04-02T18:15:47Z",
    "score": 22,
    "score_pct": 17,
    "competition_score": 0,
    "site": "linkedin"
  },
  {
    "title": "Software Engineer, Rust",
    "company": "Verse",
    "location": "",
    "level": "Entry",
    "min_exp": null,
    "max_exp": null,
    "job_url": "https://www.linkedin.com/jobs/view/4395368434",
    "date_posted": null,
    "batch_time": "2026-04-02T18:15:47Z",
    "score": 22,
    "score_pct": 17,
    "competition_score": 0,
    "site": "linkedin"
  },
  {
    "title": "Software Engineer II",
    "company": "Monogram Health",
    "location": "",
    "level": "Mid",
    "min_exp": null,
    "max_exp": null,
    "job_url": "https://www.linkedin.com/jobs/view/4397054272",
    "date_posted": null,
    "batch_time": "2026-04-02T18:15:47Z",
    "score": 22,
    "score_pct": 17,
    "competition_score": 0,
    "site": "linkedin"
  },
  {
    "title": "Software Engineer \u2013 AI Evaluation Analyst",
    "company": "Alignerr",
    "location": "",
    "level": "Entry",
    "min_exp": null,
    "max_exp": null,
    "job_url": "https://www.linkedin.com/jobs/view/4395379072",
    "date_posted": null,
    "batch_time": "2026-04-02T18:15:47Z",
    "score": 21,
    "score_pct": 16,
    "competition_score": 0,
    "site": "linkedin"
  },
  {
    "title": "Software Engineer",
    "company": "Broadcom",
    "location": "Reston, VA",
    "level": "Entry",
    "min_exp": null,
    "max_exp": null,
    "job_url": "https://www.linkedin.com/jobs/view/4393802392",
    "date_posted": null,
    "batch_time": "2026-04-02T18:15:47Z",
    "score": -999,
    "score_pct": 0,
    "competition_score": 0,
    "site": "linkedin"
  },
  {
    "title": "Software Engineer I - Implementations",
    "company": "Narmi",
    "location": "New York, NY",
    "level": "Entry",
    "min_exp": null,
    "max_exp": null,
    "job_url": "https://www.linkedin.com/jobs/view/4397064550",
    "date_posted": null,
    "batch_time": "2026-04-02T18:15:47Z",
    "score": -999,
    "score_pct": 0,
    "competition_score": 0,
    "site": "linkedin"
  },
  {
    "title": "Software Engineer",
    "company": "Hyra",
    "location": "Missouri, United States",
    "level": "Entry",
    "min_exp": null,
    "max_exp": null,
    "job_url": "https://www.linkedin.com/jobs/view/4395349916",
    "date_posted": null,
    "batch_time": "2026-04-02T18:15:47Z",
    "score": -999,
    "score_pct": 0,
    "competition_score": 0,
    "site": "linkedin"
  },
  {
    "title": "Software Engineer, iOS, Level 4",
    "company": "Snap Inc.",
    "location": "New York, United States",
    "level": "Entry",
    "min_exp": null,
    "max_exp": null,
    "job_url": "https://www.linkedin.com/jobs/view/4358305067",
    "date_posted": null,
    "batch_time": "2026-04-02T18:15:47Z",
    "score": -999,
    "score_pct": 0,
    "competition_score": 0,
    "site": "linkedin"
  },
  {
    "title": "Software Engineer I",
    "company": "Reflexive Concepts",
    "location": "Hanover, MD",
    "level": "Entry",
    "min_exp": null,
    "max_exp": null,
    "job_url": "https://www.linkedin.com/jobs/view/4395367563",
    "date_posted": null,
    "batch_time": "2026-04-02T18:15:47Z",
    "score": -999,
    "score_pct": 0,
    "competition_score": 0,
    "site": "linkedin"
  },
  {
    "title": "Software Engineer",
    "company": "Goliath Partners",
    "location": "New York, NY",
    "level": "Entry",
    "min_exp": null,
    "max_exp": null,
    "job_url": "https://www.linkedin.com/jobs/view/4395363207",
    "date_posted": null,
    "batch_time": "2026-04-02T18:15:47Z",
    "score": -999,
    "score_pct": 0,
    "competition_score": 0,
    "site": "linkedin"
  },
  {
    "title": "Software Engineer III",
    "company": "Reflexive Concepts",
    "location": "Annapolis Junction, MD",
    "level": "Mid",
    "min_exp": null,
    "max_exp": null,
    "job_url": "https://www.linkedin.com/jobs/view/4395357962",
    "date_posted": null,
    "batch_time": "2026-04-02T18:15:47Z",
    "score": -999,
    "score_pct": 0,
    "competition_score": 0,
    "site": "linkedin"
  },
  {
    "title": "Forward Deployed Software Engineer",
    "company": "OMW Consulting",
    "location": "",
    "level": "Entry",
    "min_exp": null,
    "max_exp": null,
    "job_url": "https://www.linkedin.com/jobs/view/4395349153",
    "date_posted": null,
    "batch_time": "2026-04-02T18:15:47Z",
    "score": -999,
    "score_pct": 0,
    "competition_score": 0,
    "site": "linkedin"
  },
  {
    "title": "Embedded SDE, Amazon Devices",
    "company": "Amazon",
    "location": "North Reading, MA",
    "level": "Entry",
    "min_exp": null,
    "max_exp": null,
    "job_url": "https://www.linkedin.com/jobs/view/4359330413",
    "date_posted": null,
    "batch_time": "2026-04-02T18:15:47Z",
    "score": -999,
    "score_pct": 0,
    "competition_score": 0,
    "site": "linkedin"
  },
  {
    "title": "Remote Software Engineer",
    "company": "Turing",
    "location": "Los Angeles, CA",
    "level": "Entry",
    "min_exp": null,
    "max_exp": null,
    "job_url": "https://www.linkedin.com/jobs/view/4395379079",
    "date_posted": null,
    "batch_time": "2026-04-02T18:15:47Z",
    "score": -999,
    "score_pct": 0,
    "competition_score": 0,
    "site": "linkedin"
  },
  {
    "title": "Software Engineer - Sensor Systems, Robot Software",
    "company": "Wayve",
    "location": "Sunnyvale, CA",
    "level": "Entry",
    "min_exp": null,
    "max_exp": null,
    "job_url": "https://www.linkedin.com/jobs/view/4371994599",
    "date_posted": null,
    "batch_time": "2026-04-02T18:15:47Z",
    "score": -999,
    "score_pct": 0,
    "competition_score": 0,
    "site": "linkedin"
  }
]